agenticmem_commons/__init__.py
agenticmem_commons/api_schema/__init__.py
agenticmem_commons/api_schema/internal_schema.py
agenticmem_commons/api_schema/login_schema.py
agenticmem_commons/api_schema/retriever_schema.py
agenticmem_commons/api_schema/service_schemas.py
agenticmem_commons/config_schema.py
agenticmem_commons/py.typed
agenticmem_commons-0.1.4.4.dist-info/METADATA
agenticmem_commons-0.1.4.4.dist-info/WHEEL
agenticmem_commons-0.1.4.4.dist-info/RECORD
