Metadata-Version: 2.3
Name: agenticmem-commons
Version: 0.1.4.4
Summary: 
Author: Yi Lu
Author-email: yilu331@gmail.com
Requires-Python: >=3.10,<4.0
Classifier: Programming Language :: Python :: 3
Classifier: Programming Language :: Python :: 3.10
Classifier: Programming Language :: Python :: 3.11
Classifier: Programming Language :: Python :: 3.12
Classifier: Programming Language :: Python :: 3.13
